{"ID":{"414":"b479fc4cb415df1a36b66a09fb4a04c4","0":"b479fc4cb415df1a36b66a09fb4a04c4","1":"03c427ddba885bae3f46f181e016c11b","2":"f10ae515ab08084d6cd1cb4f7d2737fb","3":"a5011ac9e6732f42c9dc1acd56af4863","4":"f532eec7451e041cf86e236eed57e548","5":"85770d25bbdd54a4dc5b185ad0e74770","6":"7629029465d114ff5f0265c3bc56fa75","7":"09662de88c814234c6be7f521548a026","8":"69447ca2eb09e8df1d20ab24824a7391","9":"d6ee3a1e9c9c8560991346f8c8db20e7","10":"e415da80db9366c498672d67cc950cf1","11":"c7daa0e883b6f82b68d2085636d721f7","12":"e2897b867a1e46e4e6437269758f3474","13":"2db3af34fc90d0f920677990d1b74807","14":"bf1561a3ff8d2303b156f581f9cd10a0","15":"d9a96dcd5ed24c841fa3f3b129b828df","16":"d0de1ffe09c2a57975b2db02eea48739","17":"bf146fd30f9b32ae635e725753bbcd4c","18":"a480cd2d6cdd18436d4ce8a79afd3ff4"},"Model":{"414":"GLS","0":"GLS","1":"FFT","2":"UnobservedComponents","3":"ARIMA","4":"AverageValueNaive","5":"DatepartRegression","6":"GLM","7":"KalmanStateSpace","8":"SeasonalNaive","9":"ETS","10":"FBProphet","11":"UnivariateMotif","12":"ARDL","13":"UnivariateRegression","14":"MetricMotif","15":"Theta","16":"SeasonalityMotif","17":"ConstantNaive","18":"LastValueNaive"},"ModelParameters":{"414":"{}","0":"{}","1":"{\"n_harmonics\": 20, \"detrend\": null}","2":"{\"level\": \"irregular\", \"maxiter\": 250, \"cov_type\": \"oim\", \"method\": \"nm\", \"autoregressive\": 1, \"regression_type\": null}","3":"{\"p\": 4, \"d\": 0, \"q\": 12, \"regression_type\": null}","4":"{\"method\": \"Mean\", \"window\": null}","5":"{\"regression_model\": {\"model\": \"KerasRNN\", \"model_params\": {\"kernel_initializer\": \"lecun_uniform\", \"epochs\": 50, \"batch_size\": 32, \"optimizer\": \"adagrad\", \"loss\": \"mae\", \"hidden_layer_sizes\": [72, 36, 72], \"rnn_type\": \"LSTM\", \"shape\": 1}}, \"datepart_method\": \"recurring\", \"polynomial_degree\": null, \"regression_type\": null}","6":"{\"family\": \"Gaussian\", \"constant\": false, \"regression_type\": null}","7":"{\"model_name\": \"local linear hidden state with seasonal 7\", \"state_transition\": [[1.0, 0.0, 0.0, 0.0, 0.0, 0.0, 0.0, 0.0], [0.0, -1.0, -1.0, -1.0, -1.0, -1.0, -1.0, 0.0], [0.0, 1.0, 0.0, 0.0, 0.0, 0.0, 0.0, 0.0], [0.0, 0.0, 1.0, 0.0, 0.0, 0.0, 0.0, 0.0], [0.0, 0.0, 0.0, 1.0, 0.0, 0.0, 0.0, 0.0], [0.0, 0.0, 0.0, 0.0, 1.0, 0.0, 0.0, 0.0], [0.0, 0.0, 0.0, 0.0, 0.0, 1.0, 0.0, 0.0], [0.0, 0.0, 0.0, 0.0, 0.0, 0.0, 1.0, 0.0]], \"process_noise\": [[0.0016, 0.0, 0.0, 0.0, 0.0, 0.0, 0.0, 0.0], [0.0, 1e-06, 0.0, 0.0, 0.0, 0.0, 0.0, 0.0], [0.0, 0.0, 0.0, 0.0, 0.0, 0.0, 0.0, 0.0], [0.0, 0.0, 0.0, 0.0, 0.0, 0.0, 0.0, 0.0], [0.0, 0.0, 0.0, 0.0, 0.0, 0.0, 0.0, 0.0], [0.0, 0.0, 0.0, 0.0, 0.0, 0.0, 0.0, 0.0], [0.0, 0.0, 0.0, 0.0, 0.0, 0.0, 0.0, 0.0], [0.0, 0.0, 0.0, 0.0, 0.0, 0.0, 0.0, 0.0]], \"observation_model\": [[1, 1, 0, 0, 0, 0, 0, 0]], \"observation_noise\": 0.5}","8":"{\"method\": \"lastvalue\", \"lag_1\": 364, \"lag_2\": 28}","9":"{\"damped_trend\": false, \"trend\": \"additive\", \"seasonal\": null, \"seasonal_periods\": null}","10":"{\"holiday\": true, \"regression_type\": null, \"growth\": \"linear\", \"n_changepoints\": 20, \"changepoint_prior_scale\": 0.1, \"seasonality_mode\": \"multiplicative\", \"changepoint_range\": 0.9, \"seasonality_prior_scale\": 10.0, \"holidays_prior_scale\": 10.0}","11":"{\"window\": 60, \"point_method\": \"median\", \"distance_metric\": \"canberra\", \"k\": 10, \"max_windows\": 10000}","12":"{\"lags\": 4, \"trend\": \"t\", \"order\": 0, \"causal\": false, \"regression_type\": \"holiday\"}","13":"{\"regression_model\": {\"model\": \"DecisionTree\", \"model_params\": {\"max_depth\": null, \"min_samples_split\": 1.0}}, \"holiday\": false, \"mean_rolling_periods\": null, \"macd_periods\": null, \"std_rolling_periods\": null, \"max_rolling_periods\": 12, \"min_rolling_periods\": 58, \"ewm_var_alpha\": null, \"ewm_alpha\": 0.5, \"additional_lag_periods\": 363, \"abs_energy\": false, \"rolling_autocorr_periods\": null, \"add_date_part\": \"simple_2_poly\", \"polynomial_degree\": null, \"x_transform\": null, \"regression_type\": null, \"window\": null}","14":"{\"window\": 10, \"point_method\": \"weighted_mean\", \"distance_metric\": \"euclidean\", \"k\": 5, \"comparison_transformation\": {\"fillna\": \"ffill\", \"transformations\": {\"0\": \"AlignLastValue\"}, \"transformation_params\": {\"0\": {\"rows\": 1, \"lag\": 2, \"method\": \"multiplicative\", \"strength\": 1.0, \"first_value_only\": false}}}, \"combination_transformation\": {\"fillna\": \"pad\", \"transformations\": {\"0\": \"AlignLastValue\"}, \"transformation_params\": {\"0\": {\"rows\": 1, \"lag\": 28, \"method\": \"additive\", \"strength\": 1.0, \"first_value_only\": false}}}}","15":"{\"deseasonalize\": true, \"difference\": false, \"use_test\": false, \"method\": \"auto\", \"period\": null, \"theta\": 2.5, \"use_mle\": true}","16":"{\"window\": 30, \"point_method\": \"weighted_mean\", \"distance_metric\": \"mqae\", \"k\": 1, \"datepart_method\": \"simple_binarized\"}","17":"{\"constant\": 1}","18":"{}"},"TransformationParameters":{"414":"{\"fillna\": \"ffill\", \"transformations\": {\"0\": \"LevelShiftTransformer\", \"1\": \"Slice\"}, \"transformation_params\": {\"0\": {\"window_size\": 90, \"alpha\": 2.5, \"grouping_forward_limit\": 3, \"max_level_shifts\": 10, \"alignment\": \"rolling_diff_3nn\"}, \"1\": {\"method\": 0.5}}}","0":"{\"fillna\": \"ffill\", \"transformations\": {\"0\": \"LevelShiftTransformer\", \"1\": \"Slice\"}, \"transformation_params\": {\"0\": {\"window_size\": 90, \"alpha\": 2.5, \"grouping_forward_limit\": 3, \"max_level_shifts\": 10, \"alignment\": \"rolling_diff_3nn\"}, \"1\": {\"method\": 0.5}}}","1":"{\"fillna\": \"ffill_mean_biased\", \"transformations\": {\"0\": \"AlignLastValue\", \"1\": \"HolidayTransformer\"}, \"transformation_params\": {\"0\": {\"rows\": 1, \"lag\": 1, \"method\": \"additive\", \"strength\": 1.0, \"first_value_only\": false}, \"1\": {\"threshold\": 0.8, \"splash_threshold\": null, \"use_dayofmonth_holidays\": true, \"use_wkdom_holidays\": true, \"use_wkdeom_holidays\": false, \"use_lunar_holidays\": false, \"use_lunar_weekday\": false, \"use_islamic_holidays\": false, \"use_hebrew_holidays\": false, \"anomaly_detector_params\": {\"method\": \"IQR\", \"method_params\": {\"iqr_threshold\": 2.5, \"iqr_quantiles\": [0.25, 0.75]}, \"fillna\": \"rolling_mean_24\", \"transform_dict\": null}, \"remove_excess_anomalies\": true, \"impact\": \"anomaly_score\", \"regression_params\": {}}}}","2":"{\"fillna\": \"rolling_mean_24\", \"transformations\": {\"0\": \"QuantileTransformer\"}, \"transformation_params\": {\"0\": {\"output_distribution\": \"normal\", \"n_quantiles\": 20}}}","3":"{\"fillna\": \"cubic\", \"transformations\": {\"0\": \"bkfilter\"}, \"transformation_params\": {\"0\": {}}}","4":"{\"fillna\": \"linear\", \"transformations\": {\"0\": \"AlignLastValue\", \"1\": \"SeasonalDifference\"}, \"transformation_params\": {\"0\": {\"rows\": 1, \"lag\": 1, \"method\": \"additive\", \"strength\": 0.5, \"first_value_only\": false}, \"1\": {\"lag_1\": 12, \"method\": \"LastValue\"}}}","5":"{\"fillna\": \"pad\", \"transformations\": {\"0\": \"AlignLastValue\"}, \"transformation_params\": {\"0\": {\"rows\": 1, \"lag\": 7, \"method\": \"additive\", \"strength\": 1.0, \"first_value_only\": false}}}","6":"{\"fillna\": \"rolling_mean\", \"transformations\": {\"0\": \"AlignLastValue\", \"1\": \"Round\"}, \"transformation_params\": {\"0\": {\"rows\": 7, \"lag\": 1, \"method\": \"additive\", \"strength\": 1.0, \"first_value_only\": false}, \"1\": {\"decimals\": 0, \"on_transform\": true, \"on_inverse\": false}}}","7":"{\"fillna\": \"nearest\", \"transformations\": {\"0\": \"RegressionFilter\", \"1\": \"AlignLastValue\", \"2\": \"PositiveShift\", \"3\": \"QuantileTransformer\", \"4\": \"ReplaceConstant\", \"5\": \"KalmanSmoothing\"}, \"transformation_params\": {\"0\": {\"sigma\": 3, \"rolling_window\": 90, \"run_order\": \"trend_first\", \"regression_params\": {\"regression_model\": {\"model\": \"DecisionTree\", \"model_params\": {\"max_depth\": 9, \"min_samples_split\": 1.0}}, \"datepart_method\": \"expanded\", \"polynomial_degree\": null, \"transform_dict\": null, \"holiday_countries_used\": true}, \"holiday_params\": null}, \"1\": {\"rows\": 2, \"lag\": 1, \"method\": \"additive\", \"strength\": 0.2, \"first_value_only\": false}, \"2\": {}, \"3\": {\"output_distribution\": \"uniform\", \"n_quantiles\": 1000}, \"4\": {\"constant\": 0, \"reintroduction_model\": {\"model\": \"RandomForest\", \"model_params\": {\"n_estimators\": 100, \"min_samples_leaf\": 4, \"bootstrap\": true}, \"datepart_method\": \"simple\"}, \"fillna\": \"akima\"}, \"5\": {\"model_name\": \"dynamic linear\", \"state_transition\": [[1, 1, 0, 0], [0, 1, 0, 0], [0, 0, 0.6, 1], [0, 0, 0.3, 0]], \"process_noise\": [[1.0, 0, 0, 0], [0, 0.7, 0, 0], [0, 0, 0.3, 0], [0, 0, 0, 0]], \"observation_model\": [[1, 0, 1, 0]], \"observation_noise\": 0.25, \"em_iter\": 10}}}","8":"{\"fillna\": \"fake_date\", \"transformations\": {\"0\": \"RobustScaler\", \"1\": \"AlignLastValue\"}, \"transformation_params\": {\"0\": {}, \"1\": {\"rows\": 1, \"lag\": 1, \"method\": \"additive\", \"strength\": 1.0, \"first_value_only\": false}}}","9":"{\"fillna\": \"fake_date\", \"transformations\": {\"0\": \"ClipOutliers\", \"1\": \"SeasonalDifference\"}, \"transformation_params\": {\"0\": {\"method\": \"clip\", \"std_threshold\": 4, \"fillna\": null}, \"1\": {\"lag_1\": 12, \"method\": \"Mean\"}}}","10":"{\"fillna\": \"pchip\", \"transformations\": {\"0\": \"AlignLastValue\", \"1\": \"SeasonalDifference\"}, \"transformation_params\": {\"0\": {\"rows\": 7, \"lag\": 7, \"method\": \"additive\", \"strength\": 1.0, \"first_value_only\": false}, \"1\": {\"lag_1\": 12, \"method\": \"Mean\"}}}","11":"{\"fillna\": \"zero\", \"transformations\": {\"0\": \"bkfilter\", \"1\": \"LevelShiftTransformer\", \"2\": \"LevelShiftTransformer\", \"3\": \"Round\", \"4\": \"MaxAbsScaler\"}, \"transformation_params\": {\"0\": {}, \"1\": {\"window_size\": 30, \"alpha\": 3.5, \"grouping_forward_limit\": 4, \"max_level_shifts\": 30, \"alignment\": \"average\"}, \"2\": {\"window_size\": 90, \"alpha\": 2.5, \"grouping_forward_limit\": 2, \"max_level_shifts\": 10, \"alignment\": \"rolling_diff\"}, \"3\": {\"decimals\": 2, \"on_transform\": false, \"on_inverse\": true}, \"4\": {}}}","12":"{\"fillna\": \"fake_date\", \"transformations\": {\"0\": \"IntermittentOccurrence\"}, \"transformation_params\": {\"0\": {\"center\": \"mean\"}}}","13":"{\"fillna\": \"rolling_mean\", \"transformations\": {\"0\": \"MaxAbsScaler\", \"1\": \"SeasonalDifference\", \"2\": \"Round\"}, \"transformation_params\": {\"0\": {}, \"1\": {\"lag_1\": 7, \"method\": \"LastValue\"}, \"2\": {\"decimals\": -2, \"on_transform\": false, \"on_inverse\": true}}}","14":"{\"fillna\": \"fake_date\", \"transformations\": {\"0\": \"ClipOutliers\", \"1\": \"Detrend\", \"2\": \"QuantileTransformer\", \"3\": \"AlignLastValue\"}, \"transformation_params\": {\"0\": {\"method\": \"clip\", \"std_threshold\": 4, \"fillna\": null}, \"1\": {\"model\": \"Linear\", \"phi\": 1, \"window\": null, \"transform_dict\": null}, \"2\": {\"output_distribution\": \"uniform\", \"n_quantiles\": 100}, \"3\": {\"rows\": 1, \"lag\": 1, \"method\": \"additive\", \"strength\": 1.0, \"first_value_only\": false}}}","15":"{\"fillna\": \"mean\", \"transformations\": {\"0\": \"Detrend\", \"1\": \"LocalLinearTrend\"}, \"transformation_params\": {\"0\": {\"model\": \"Linear\", \"phi\": 1, \"window\": 90}, \"1\": {\"rolling_window\": 0.1, \"n_tails\": 90, \"n_future\": 360, \"method\": \"median\", \"macro_micro\": true}}}","16":"{\"fillna\": \"akima\", \"transformations\": {\"0\": \"StandardScaler\", \"1\": \"DifferencedTransformer\"}, \"transformation_params\": {\"0\": {}, \"1\": {}}}","17":"{\"fillna\": \"quadratic\", \"transformations\": {\"0\": \"ScipyFilter\", \"1\": \"StandardScaler\", \"2\": \"SeasonalDifference\", \"3\": \"KalmanSmoothing\"}, \"transformation_params\": {\"0\": {\"method\": \"savgol_filter\", \"method_args\": {\"window_length\": 91, \"polyorder\": 3, \"deriv\": 0, \"mode\": \"interp\"}}, \"1\": {}, \"2\": {\"lag_1\": 12, \"method\": \"Mean\"}, \"3\": {\"model_name\": \"MA\", \"state_transition\": [[1, 0], [1, 0]], \"process_noise\": [[0.2, 0.0], [0.0, 0]], \"observation_model\": [[1, 0.1]], \"observation_noise\": 1.0, \"em_iter\": null}}}","18":"{\"fillna\": \"fake_date\", \"transformations\": {\"0\": \"IntermittentOccurrence\", \"1\": \"SinTrend\", \"2\": \"PowerTransformer\"}, \"transformation_params\": {\"0\": {\"center\": \"mean\"}, \"1\": {}, \"2\": {}}}"},"Ensemble":{"414":0,"0":0,"1":0,"2":0,"3":0,"4":0,"5":0,"6":0,"7":0,"8":0,"9":0,"10":0,"11":0,"12":0,"13":0,"14":0,"15":0,"16":0,"17":0,"18":0},"Runs":{"414":4,"0":4,"1":4,"2":4,"3":4,"4":4,"5":4,"6":4,"7":4,"8":4,"9":4,"10":4,"11":4,"12":4,"13":4,"14":4,"15":4,"16":4,"17":4,"18":4},"smape":{"414":32.0452447549,"0":32.0452447549,"1":45.3452553119,"2":39.7500386074,"3":38.8168315413,"4":43.4730734892,"5":40.4088619794,"6":39.4278004132,"7":39.1867173675,"8":36.5341523085,"9":39.7027493832,"10":46.904491762,"11":36.8190011017,"12":57.9869462456,"13":39.5571044687,"14":46.9021616845,"15":53.4932328873,"16":41.8497878287,"17":55.135120643,"18":61.2010342568},"mae":{"414":8011.238038145,"0":8011.238038145,"1":8263.2216158531,"2":9093.5359724584,"3":10690.5639924995,"4":9630.482590089,"5":11200.802013098,"6":11303.3777977564,"7":11545.5851818683,"8":11591.488705471,"9":11874.668275526,"10":12525.4254798458,"11":9586.0075732573,"12":13943.4615399974,"13":11295.0673568161,"14":13304.3009151399,"15":17733.9510829585,"16":13346.4905159571,"17":13671.5300764305,"18":13849.0863486926},"rmse":{"414":10902.14637997,"0":10902.14637997,"1":10895.4938719627,"2":12027.6446138684,"3":13549.4535046805,"4":12582.3598634131,"5":14048.0117309075,"6":14211.4028382557,"7":14489.4461658903,"8":15052.6799553123,"9":14990.4318361756,"10":17646.4770302623,"11":12554.9102569187,"12":16483.6771427946,"13":14209.1405053571,"14":15868.428119483,"15":21124.0607859384,"16":17705.7831260136,"17":16234.7866979876,"18":16339.5311794198},"made":{"414":1.5407626414,"0":1.5407626414,"1":1.5340079962,"2":1.5241375898,"3":1.5221286247,"4":2.4009735745,"5":1.526284757,"6":1.5219970571,"7":1.678789181,"8":1.9814239249,"9":1.5333948704,"10":1.7695010019,"11":1.5722626497,"12":1.5591767949,"13":2.2613249315,"14":1.6918206232,"15":1.5273016419,"16":1.9943278615,"17":1.5655660716,"18":1.5565393981},"mage":{"414":63569.7568759694,"0":63569.7568759694,"1":64891.0882027394,"2":71050.5273277644,"3":84645.5834018946,"4":76576.0077983563,"5":89221.0761616648,"6":90076.3049030152,"7":91742.3596969318,"8":91463.8032105447,"9":94182.8496631075,"10":99805.0167334482,"11":73431.946315151,"12":110480.077809211,"13":89875.7342558116,"14":104649.723009177,"15":141512.972258552,"16":105984.9547604898,"17":109287.4935788834,"18":110732.7034226314},"underestimate":{"414":-8515887.1683885828,"0":-8515887.1683885828,"1":-9117011.6593632512,"2":-7192843.1324024107,"3":-5619450.2035692176,"4":-11516904.3412729688,"5":-5589337.8039233182,"6":-5303224.2235145234,"7":-5113806.9343441837,"8":-4703880.567924438,"9":-5322006.5652344199,"10":-8111432.354525757,"11":-6990534.6470372528,"12":-18544030.9078714438,"13":-5343295.9643291272,"14":-12382360.9627532028,"15":-5325963.3093725638,"16":-6429709.7011337532,"17":-16675468.1958636884,"18":-17724753.5141846612},"mle":{"414":6246.3041704953,"0":6246.3041704953,"1":6686.5832783738,"2":5276.5811000513,"3":4124.4575699417,"4":8445.234148454,"5":4102.5131050413,"6":3892.9522640039,"7":3754.2971672776,"8":3454.2253891169,"9":3906.9340665581,"10":5950.3581935994,"11":5128.8283384851,"12":13596.6177949098,"13":3922.3202881206,"14":9082.0728473727,"15":3911.1646413232,"16":4718.4743686604,"17":12227.1691477397,"18":12996.1894720386},"overestimate":{"414":2411441.5156412115,"0":2411441.5156412115,"1":2154022.6246604309,"2":5210739.9340307824,"3":8962479.08220011,"4":1619073.9116084604,"5":9688556.1419423036,"6":10114583.0926251523,"7":10634371.2537242081,"8":11106910.0263380632,"9":10875040.9625830017,"10":8973247.9999839365,"11":6084779.6828857493,"12":474850.6326850616,"13":10063175.9103680011,"14":5764705.4854976144,"15":18863145.9677828364,"16":11774903.3626317531,"17":1972498.8283874553,"18":1165400.265432063},"imle":{"414":1773.1501069051,"0":1773.1501069051,"1":1585.1181877878,"2":3825.3874300802,"3":6574.5448906573,"4":1193.8544710934,"5":7106.8170982201,"6":7418.8954398761,"7":7799.7339982267,"8":8145.6512204071,"9":7976.2425109002,"10":6583.6719693969,"11":4465.4973650286,"12":355.3878995706,"13":7381.2347270279,"14":4230.8525864762,"15":13831.8181246595,"16":8636.6188494786,"17":1453.1872601517,"18":861.784059445},"spl":{"414":14.340389718,"0":14.340389718,"1":14.1959029832,"2":14.2047206078,"3":13.3560347645,"4":13.9279306694,"5":13.7173005005,"6":13.7692922812,"7":13.5188588394,"8":13.5914594252,"9":13.9769297939,"10":12.6690125348,"11":22.4525177764,"12":17.705152768,"13":23.9910427063,"14":20.990870776,"15":17.2755258265,"16":25.7754314587,"17":27.316879169,"18":29.1097669365},"containment":{"414":0.8101173021,"0":0.8101173021,"1":0.8441165689,"2":0.8508980938,"3":0.758431085,"4":0.7318548387,"5":0.8164406158,"6":0.8213892962,"7":0.8607038123,"8":0.8026026393,"9":0.8335777126,"10":0.6251832845,"11":0.0830278592,"12":0.5845857771,"13":0.0,"14":0.1785190616,"15":0.6125366569,"16":0.0,"17":0.0,"18":0.0394978006},"contour":{"414":0.5089809384,"0":0.5089809384,"1":0.5087060117,"2":0.491202346,"3":0.5031158358,"4":0.4897360704,"5":0.5067815249,"6":0.5093475073,"7":0.496792522,"8":0.5143878299,"9":0.4772727273,"10":0.4819464809,"11":0.5008247801,"12":0.4953262463,"13":0.5156708211,"14":0.5027492669,"15":0.4914772727,"16":0.4831378299,"17":0.5043071848,"18":0.4878115836},"maxe":{"414":53178.4105112315,"0":53178.4105112315,"1":55867.9000685274,"2":55597.8359821663,"3":54176.9403916116,"4":54934.6047652834,"5":53537.4970335549,"6":52982.4152831747,"7":52688.4396231444,"8":52947.303466875,"9":52755.7612878952,"10":88516.7436474675,"11":53706.69246125,"12":57061.4938129694,"13":52993.296203625,"14":49226.4846577062,"15":71589.7900219575,"16":72584.767699625,"17":53855.9620545126,"18":56233.3811060332},"oda":{"414":0.5963159824,"0":0.5963159824,"1":0.5903592375,"2":0.5736803519,"3":0.5556268328,"4":0.5916422287,"5":0.5305168622,"6":0.5254765396,"7":0.5336326979,"8":0.6386546921,"9":0.6435117302,"10":0.5098057185,"11":0.6987719941,"12":0.5902675953,"13":0.4451979472,"14":0.7759347507,"15":0.4070747801,"16":0.5278592375,"17":0.5916422287,"18":0.5916422287},"dwae":{"414":473.3302118667,"0":473.3302118667,"1":532.5312322781,"2":480.1834056615,"3":456.667729227,"4":543.9724055524,"5":460.2865885945,"6":452.7513334012,"7":437.6959180052,"8":369.9677869257,"9":298.6138962802,"10":749.2030374111,"11":434.2122626553,"12":545.1782169822,"13":525.8043617705,"14":163.5745311374,"15":763.4033701296,"16":625.1124827967,"17":554.5744965646,"18":570.3541083558},"mqae":{"414":5591.7293639493,"0":5591.7293639493,"1":5934.4072564985,"2":6631.1085758913,"3":8371.523397217,"4":6999.3420506815,"5":8851.4967997398,"6":8946.6731328963,"7":9177.6105418226,"8":8643.7503223359,"9":9244.0390964573,"10":8108.1788466975,"11":7223.9036286383,"12":11446.679323874,"13":8914.5086909681,"14":10812.7777463622,"15":14516.3505958909,"16":9444.8874933894,"17":11148.7508005175,"18":11344.0837258853},"ewmae":{"414":39987.20881736,"0":39987.20881736,"1":40800.4017900181,"2":45208.3664534325,"3":53486.6100157724,"4":46067.1717826538,"5":56526.4699650183,"6":57159.8301993884,"7":58160.2872936516,"8":62007.2370429309,"9":63230.9369128388,"10":73967.3335767182,"11":48685.188171028,"12":64750.711385171,"13":57032.9499825081,"14":64590.2241377368,"15":91724.3161812089,"16":72188.2401242022,"17":62555.9908882524,"18":63922.3504013355},"uwmse":{"414":3418376.1428845404,"0":3418376.1428845404,"1":3388793.6281386404,"2":3420006.2801122852,"3":3243874.6539182588,"4":3981810.156616448,"5":3211794.1880992283,"6":3145566.3288374464,"7":3122591.229446495,"8":3233923.9531124118,"9":3378817.1752594924,"10":4851865.4610317275,"11":3125003.0190746393,"12":4766452.361728658,"13":3151037.8941311897,"14":2819996.7696240563,"15":4425016.411746013,"16":3768838.4146972946,"17":4607526.512760995,"18":4961544.1488604303},"smoothness":{"414":2.360036601,"0":2.360036601,"1":1.277305417,"2":0.6434598321,"3":2.6082182641,"4":6.9261431117,"5":1.5080818203,"6":1.012810486,"7":5.4919087341,"8":6.455733694,"9":3.8629472951,"10":5.1515091575,"11":3.9509083198,"12":3.3465655658,"13":6.876586547,"14":5.0630593353,"15":3.2354087838,"16":6.3825238588,"17":3.7154272023,"18":2.5526523165},"mate":{"414":2053658.1834002021,"0":2053658.1834002021,"1":1972807.9201538474,"2":2545220.5499561424,"3":3460611.5123343319,"4":2811150.7123028934,"5":3605215.9239126444,"6":3645359.6959953699,"7":3736330.0320107201,"8":3690550.6858284064,"9":3798260.3556044241,"10":3654269.1666351277,"11":2860464.2324044378,"12":4519741.476899446,"13":3635303.5073706564,"14":4075146.3624980566,"15":5953117.9112336142,"16":3812889.6403630637,"17":4267061.2703984762,"18":4475123.311376011},"wasserstein":{"414":1656.0553380977,"0":1656.0553380977,"1":3135.8953222372,"2":2507.5080974756,"3":2262.9324091637,"4":2942.9710721911,"5":2339.3976346266,"6":2190.6949847548,"7":2120.6266570761,"8":1723.19969379,"9":2048.9555938362,"10":2715.4637289027,"11":2148.0493597865,"12":2932.5252286871,"13":2199.5084629891,"14":1847.6654874598,"15":3152.9469574222,"16":2005.890015305,"17":3045.101481168,"18":3402.4550001776},"dwd":{"414":216.5833363713,"0":216.5833363713,"1":198.3263243418,"2":213.6463693828,"3":212.2016750934,"4":85.9778200547,"5":221.5160127582,"6":222.8431459433,"7":139.8830459313,"8":91.0757773794,"9":208.5206011202,"10":148.5884474097,"11":194.2376748852,"12":204.6455998677,"13":83.9222067713,"14":156.169159495,"15":208.6139239791,"16":146.0297708691,"17":203.350441217,"18":205.3956428598},"smape_weighted":{"414":32.0452447549,"0":32.0452447549,"1":45.3452553119,"2":39.7500386074,"3":38.8168315413,"4":43.4730734892,"5":40.4088619794,"6":39.4278004132,"7":39.1867173675,"8":36.5341523085,"9":39.7027493832,"10":46.904491762,"11":36.8190011017,"12":57.9869462456,"13":39.5571044687,"14":46.9021616845,"15":53.4932328873,"16":41.8497878287,"17":55.135120643,"18":61.2010342568},"mae_weighted":{"414":8011.238038145,"0":8011.238038145,"1":8263.2216158531,"2":9093.5359724584,"3":10690.5639924995,"4":9630.482590089,"5":11200.802013098,"6":11303.3777977564,"7":11545.5851818683,"8":11591.488705471,"9":11874.668275526,"10":12525.4254798458,"11":9586.0075732573,"12":13943.4615399974,"13":11295.0673568161,"14":13304.3009151399,"15":17733.9510829585,"16":13346.4905159571,"17":13671.5300764305,"18":13849.0863486926},"rmse_weighted":{"414":10902.14637997,"0":10902.14637997,"1":10895.4938719627,"2":12027.6446138684,"3":13549.4535046805,"4":12582.3598634131,"5":14048.0117309075,"6":14211.4028382557,"7":14489.4461658903,"8":15052.6799553123,"9":14990.4318361756,"10":17646.4770302623,"11":12554.9102569187,"12":16483.6771427946,"13":14209.1405053571,"14":15868.428119483,"15":21124.0607859384,"16":17705.7831260136,"17":16234.7866979876,"18":16339.5311794198},"made_weighted":{"414":1.5407626414,"0":1.5407626414,"1":1.5340079962,"2":1.5241375898,"3":1.5221286247,"4":2.4009735745,"5":1.526284757,"6":1.5219970571,"7":1.678789181,"8":1.9814239249,"9":1.5333948704,"10":1.7695010019,"11":1.5722626497,"12":1.5591767949,"13":2.2613249315,"14":1.6918206232,"15":1.5273016419,"16":1.9943278615,"17":1.5655660716,"18":1.5565393981},"mage_weighted":{"414":63569.7568759694,"0":63569.7568759694,"1":64891.0882027394,"2":71050.5273277644,"3":84645.5834018946,"4":76576.0077983563,"5":89221.0761616648,"6":90076.3049030152,"7":91742.3596969318,"8":91463.8032105447,"9":94182.8496631075,"10":99805.0167334482,"11":73431.946315151,"12":110480.077809211,"13":89875.7342558116,"14":104649.723009177,"15":141512.972258552,"16":105984.9547604898,"17":109287.4935788834,"18":110732.7034226314},"mle_weighted":{"414":6246.3041704953,"0":6246.3041704953,"1":6686.5832783738,"2":5276.5811000513,"3":4124.4575699417,"4":8445.234148454,"5":4102.5131050413,"6":3892.9522640039,"7":3754.2971672776,"8":3454.2253891169,"9":3906.9340665581,"10":5950.3581935994,"11":5128.8283384851,"12":13596.6177949098,"13":3922.3202881206,"14":9082.0728473727,"15":3911.1646413232,"16":4718.4743686604,"17":12227.1691477397,"18":12996.1894720386},"imle_weighted":{"414":1773.1501069051,"0":1773.1501069051,"1":1585.1181877878,"2":3825.3874300802,"3":6574.5448906573,"4":1193.8544710934,"5":7106.8170982201,"6":7418.8954398761,"7":7799.7339982267,"8":8145.6512204071,"9":7976.2425109002,"10":6583.6719693969,"11":4465.4973650286,"12":355.3878995706,"13":7381.2347270279,"14":4230.8525864762,"15":13831.8181246595,"16":8636.6188494786,"17":1453.1872601517,"18":861.784059445},"spl_weighted":{"414":14.340389718,"0":14.340389718,"1":14.1959029832,"2":14.2047206078,"3":13.3560347645,"4":13.9279306694,"5":13.7173005005,"6":13.7692922812,"7":13.5188588394,"8":13.5914594252,"9":13.9769297939,"10":12.6690125348,"11":22.4525177764,"12":17.705152768,"13":23.9910427063,"14":20.990870776,"15":17.2755258265,"16":25.7754314587,"17":27.316879169,"18":29.1097669365},"maxe_weighted":{"414":53178.4105112315,"0":53178.4105112315,"1":55867.9000685274,"2":55597.8359821663,"3":54176.9403916116,"4":54934.6047652834,"5":53537.4970335549,"6":52982.4152831747,"7":52688.4396231444,"8":52947.303466875,"9":52755.7612878952,"10":88516.7436474675,"11":53706.69246125,"12":57061.4938129694,"13":52993.296203625,"14":49226.4846577062,"15":71589.7900219575,"16":72584.767699625,"17":53855.9620545126,"18":56233.3811060332},"oda_weighted":{"414":0.5963159824,"0":0.5963159824,"1":0.5903592375,"2":0.5736803519,"3":0.5556268328,"4":0.5916422287,"5":0.5305168622,"6":0.5254765396,"7":0.5336326979,"8":0.6386546921,"9":0.6435117302,"10":0.5098057185,"11":0.6987719941,"12":0.5902675953,"13":0.4451979472,"14":0.7759347507,"15":0.4070747801,"16":0.5278592375,"17":0.5916422287,"18":0.5916422287},"dwae_weighted":{"414":473.3302118667,"0":473.3302118667,"1":532.5312322781,"2":480.1834056615,"3":456.667729227,"4":543.9724055524,"5":460.2865885945,"6":452.7513334012,"7":437.6959180052,"8":369.9677869257,"9":298.6138962802,"10":749.2030374111,"11":434.2122626553,"12":545.1782169822,"13":525.8043617705,"14":163.5745311374,"15":763.4033701296,"16":625.1124827967,"17":554.5744965646,"18":570.3541083558},"mqae_weighted":{"414":5591.7293639493,"0":5591.7293639493,"1":5934.4072564985,"2":6631.1085758913,"3":8371.523397217,"4":6999.3420506815,"5":8851.4967997398,"6":8946.6731328963,"7":9177.6105418226,"8":8643.7503223359,"9":9244.0390964573,"10":8108.1788466975,"11":7223.9036286383,"12":11446.679323874,"13":8914.5086909681,"14":10812.7777463622,"15":14516.3505958909,"16":9444.8874933894,"17":11148.7508005175,"18":11344.0837258853},"ewmae_weighted":{"414":39987.20881736,"0":39987.20881736,"1":40800.4017900181,"2":45208.3664534325,"3":53486.6100157724,"4":46067.1717826538,"5":56526.4699650183,"6":57159.8301993884,"7":58160.2872936516,"8":62007.2370429309,"9":63230.9369128388,"10":73967.3335767182,"11":48685.188171028,"12":64750.711385171,"13":57032.9499825081,"14":64590.2241377368,"15":91724.3161812089,"16":72188.2401242022,"17":62555.9908882524,"18":63922.3504013355},"uwmse_weighted":{"414":3418376.1428845404,"0":3418376.1428845404,"1":3388793.6281386404,"2":3420006.2801122852,"3":3243874.6539182588,"4":3981810.156616448,"5":3211794.1880992283,"6":3145566.3288374464,"7":3122591.229446495,"8":3233923.9531124118,"9":3378817.1752594924,"10":4851865.4610317275,"11":3125003.0190746393,"12":4766452.361728658,"13":3151037.8941311897,"14":2819996.7696240563,"15":4425016.411746013,"16":3768838.4146972946,"17":4607526.512760995,"18":4961544.1488604303},"smoothness_weighted":{"414":2.360036601,"0":2.360036601,"1":1.277305417,"2":0.6434598321,"3":2.6082182641,"4":6.9261431117,"5":1.5080818203,"6":1.012810486,"7":5.4919087341,"8":6.455733694,"9":3.8629472951,"10":5.1515091575,"11":3.9509083198,"12":3.3465655658,"13":6.876586547,"14":5.0630593353,"15":3.2354087838,"16":6.3825238588,"17":3.7154272023,"18":2.5526523165},"mate_weighted":{"414":2053658.1834002021,"0":2053658.1834002021,"1":1972807.9201538474,"2":2545220.5499561424,"3":3460611.5123343319,"4":2811150.7123028934,"5":3605215.9239126444,"6":3645359.6959953699,"7":3736330.0320107201,"8":3690550.6858284064,"9":3798260.3556044241,"10":3654269.1666351277,"11":2860464.2324044378,"12":4519741.476899446,"13":3635303.5073706564,"14":4075146.3624980566,"15":5953117.9112336142,"16":3812889.6403630637,"17":4267061.2703984762,"18":4475123.311376011},"wasserstein_weighted":{"414":1656.0553380977,"0":1656.0553380977,"1":3135.8953222372,"2":2507.5080974756,"3":2262.9324091637,"4":2942.9710721911,"5":2339.3976346266,"6":2190.6949847548,"7":2120.6266570761,"8":1723.19969379,"9":2048.9555938362,"10":2715.4637289027,"11":2148.0493597865,"12":2932.5252286871,"13":2199.5084629891,"14":1847.6654874598,"15":3152.9469574222,"16":2005.890015305,"17":3045.101481168,"18":3402.4550001776},"dwd_weighted":{"414":216.5833363713,"0":216.5833363713,"1":198.3263243418,"2":213.6463693828,"3":212.2016750934,"4":85.9778200547,"5":221.5160127582,"6":222.8431459433,"7":139.8830459313,"8":91.0757773794,"9":208.5206011202,"10":148.5884474097,"11":194.2376748852,"12":204.6455998677,"13":83.9222067713,"14":156.169159495,"15":208.6139239791,"16":146.0297708691,"17":203.350441217,"18":205.3956428598},"containment_weighted":{"414":0.8101173021,"0":0.8101173021,"1":0.8441165689,"2":0.8508980938,"3":0.758431085,"4":0.7318548387,"5":0.8164406158,"6":0.8213892962,"7":0.8607038123,"8":0.8026026393,"9":0.8335777126,"10":0.6251832845,"11":0.0830278592,"12":0.5845857771,"13":0.0,"14":0.1785190616,"15":0.6125366569,"16":0.0,"17":0.0,"18":0.0394978006},"contour_weighted":{"414":0.5089809384,"0":0.5089809384,"1":0.5087060117,"2":0.491202346,"3":0.5031158358,"4":0.4897360704,"5":0.5067815249,"6":0.5093475073,"7":0.496792522,"8":0.5143878299,"9":0.4772727273,"10":0.4819464809,"11":0.5008247801,"12":0.4953262463,"13":0.5156708211,"14":0.5027492669,"15":0.4914772727,"16":0.4831378299,"17":0.5043071848,"18":0.4878115836},"TotalRuntimeSeconds":{"414":0.5248,"0":0.5248,"1":0.490425,"2":1.29755,"3":44.2188,"4":0.0088,"5":18.5394,"6":0.56765,"7":11.799025,"8":0.56,"9":0.66685,"10":2.973025,"11":0.654,"12":0.0831,"13":2.016375,"14":0.039525,"15":1.690775,"16":0.026825,"17":0.350625,"18":0.0709},"Score":{"414":85.0931662039,"0":85.0931662039,"1":89.9323478815,"2":90.940849115,"3":93.0747713886,"4":94.1016060527,"5":96.1559386131,"6":96.3171083001,"7":96.5756153689,"8":96.8781284794,"9":99.1249642031,"10":103.2789752106,"11":112.8117390058,"12":120.8600249178,"13":123.4960317431,"14":123.5088938515,"15":130.8234299356,"16":137.0956814288,"17":143.865092335,"18":151.250070438},"lowest_series_mape":{"414":105.1013212705,"0":105.1013212705,"1":125.5292145625,"2":116.2945468163,"3":109.5728831751,"4":118.0292377118,"5":112.8363399511,"6":121.2143103339,"7":119.0798449191,"8":124.8244987243,"9":131.7912752315,"10":180.74992821,"11":102.785866671,"12":264.4651286047,"13":120.4925084207,"14":188.9028964345,"15":265.7158298894,"16":180.1236790761,"17":223.5152150375,"18":234.9713534189},"lowest_series_mape_name":{"414":"Closed_7_ago","0":"Closed_7_ago","1":"Closed_7_ago","2":"Closed_7_ago","3":"Closed_7_ago","4":"Closed_6_ago","5":"Closed_2_ago","6":"Closed_7_ago","7":"Closed_7_ago","8":"Closed_7_ago","9":"Closed_7_ago","10":"Closed_7_ago","11":"Closed_7_ago","12":"Close","13":"Closed_7_ago","14":"Close","15":"Closed_7_ago","16":"Closed_7_ago","17":"Close","18":"Close"},"highest_series_mape":{"414":112.7467798517,"0":112.7467798517,"1":130.1551197157,"2":134.2844459222,"3":131.5844913392,"4":121.9803374009,"5":137.3141808582,"6":134.1725257203,"7":140.3540132486,"8":180.501748537,"9":135.5889013055,"10":193.9414531386,"11":114.2973013062,"12":272.9219151546,"13":133.3910097211,"14":199.2335592474,"15":329.3870577328,"16":235.0454697992,"17":231.9131161481,"18":247.0510831823},"highest_series_mape_name":{"414":"Close","0":"Close","1":"Closed_3_ago","2":"Closed_1_ago","3":"Close","4":"Closed_3_ago","5":"Closed_6_ago","6":"Close","7":"Closed_2_ago","8":"Close","9":"Closed_1_ago","10":"Closed_2_ago","11":"Close","12":"Closed_7_ago","13":"Close","14":"Closed_7_ago","15":"Closed_1_ago","16":"Closed_1_ago","17":"Closed_7_ago","18":"Closed_7_ago"},"index":{"414":null,"0":414.0,"1":14.0,"2":557.0,"3":379.0,"4":568.0,"5":308.0,"6":279.0,"7":25.0,"8":253.0,"9":493.0,"10":530.0,"11":462.0,"12":528.0,"13":109.0,"14":445.0,"15":500.0,"16":479.0,"17":444.0,"18":378.0}}